__init__.py
blubber_orm/__init__.py
blubber_orm/models/__init__.py
blubber_orm/models/_base.py
blubber_orm/models/_conn.py
blubber_orm/models/_utils.py
blubber_orm/utils/__init__.py
blubber_orm/utils/config.py
blubber_orm/utils/uid_generator.py
blubber_orm/versions/blubber_cli.py
blubber_orm-2.0.6.dist-info/LICENSE
blubber_orm-2.0.6.dist-info/METADATA
blubber_orm-2.0.6.dist-info/WHEEL
blubber_orm-2.0.6.dist-info/top_level.txt
blubber_orm-2.0.6.dist-info/RECORD
