Metadata-Version: 2.1
Name: blubber-orm
Version: 2.0.6
Summary: Simple Postgres access for Python Apps through psycopg2.
Author-email: Ade Balogun <ade.d.balogun@gmail.com>
License: Apache License
Project-URL: Homepage, https://github.com/hubbub-tech/blubber-orm
Project-URL: Bug Tracker, https://github.com/hubbub-tech/blubber-orm/issues
Keywords: blubber,orm,psycopg2
Classifier: Programming Language :: Python :: 3
Classifier: Operating System :: OS Independent
Requires-Python: >=3.6
License-File: LICENSE
Requires-Dist: DateTime (>=4.3)
Requires-Dist: psycopg2 (>=2.9.3)
Requires-Dist: pytz (>=2021.1)
Requires-Dist: uritools (==3.0.2)
Requires-Dist: Werkzeug (>=2.0.1)
Requires-Dist: zope.interface (>=5.4.0)
